pyrfra/__init__.py
pyrfra/functional/__init__.py
pyrfra/functional/iterators.py
pyrfra/remote/__init__.py
pyrfra/remote/wrapper.py
pyrfra/utils/__init__.py
pyrfra/utils/files.py
pyrfra/utils/shell.py
pyrfra-0.0.1.dist-info/METADATA
pyrfra-0.0.1.dist-info/WHEEL
pyrfra-0.0.1.dist-info/top_level.txt
pyrfra-0.0.1.dist-info/RECORD
