Metadata-Version: 2.1
Name: pyrfra
Version: 0.0.1
Summary: A framework for research code
Home-page: https://github.com/EleutherAI/pyrfra
Author: Leo Gao
Author-email: lg@eleuther.ai
License: UNKNOWN
Platform: UNKNOWN
Classifier: Programming Language :: Python :: 3
Classifier: License :: OSI Approved :: MIT License
Classifier: Operating System :: OS Independent
Requires-Python: >=3.6
